django_static_jquery3/.DS_Store
django_static_jquery3/__init__.py
django_static_jquery3/admin.py
django_static_jquery3/apps.py
django_static_jquery3/models.py
django_static_jquery3/tests.py
django_static_jquery3/views.py
django_static_jquery3/migrations/__init__.py
django_static_jquery3/static/.DS_Store
django_static_jquery3/static/jquery/.DS_Store
django_static_jquery3/static/jquery/jquery.js
django_static_jquery3/static/jquery/jquery.min.js
django_static_jquery3/static/jquery/jquery.min.map
django_static_jquery3/static/jquery/jquery.slim.js
django_static_jquery3/static/jquery/jquery.slim.min.js
django_static_jquery3/static/jquery/jquery.slim.min.map
django_static_jquery3/static/jquery/licenses/.DS_Store
django_static_jquery3/static/jquery/licenses/jquery/LICENSE.txt
django_static_jquery3/static/jquery/licenses/jquery.cookie/MIT-LICENSE.txt
django_static_jquery3/static/jquery/licenses/jquery.jstree/.DS_Store
django_static_jquery3/static/jquery/licenses/jquery.jstree/LICENSE-MIT
django_static_jquery3/static/jquery/plugins/.DS_Store
django_static_jquery3/static/jquery/plugins/jquery.cookie.js
django_static_jquery3/static/jquery/plugins/jquery.parseQuery.js
django_static_jquery3/static/jquery/plugins/jquery.utils.js
django_static_jquery3/static/jquery/plugins/jquery.jstree/.DS_Store
django_static_jquery3/static/jquery/plugins/jquery.jstree/jstree.js
django_static_jquery3/static/jquery/plugins/jquery.jstree/jstree.min.js
django_static_jquery3/static/jquery/plugins/jquery.jstree/themes/default/32px.png
django_static_jquery3/static/jquery/plugins/jquery.jstree/themes/default/40px.png
django_static_jquery3/static/jquery/plugins/jquery.jstree/themes/default/style.css
django_static_jquery3/static/jquery/plugins/jquery.jstree/themes/default/style.min.css
django_static_jquery3/static/jquery/plugins/jquery.jstree/themes/default/throbber.gif
django_static_jquery3/static/jquery/plugins/jquery.jstree/themes/default-dark/32px.png
django_static_jquery3-6.3.7.2.dist-info/licenses/LICENSE
django_static_jquery3-6.3.7.2.dist-info/METADATA
django_static_jquery3-6.3.7.2.dist-info/WHEEL
django_static_jquery3-6.3.7.2.dist-info/top_level.txt
django_static_jquery3-6.3.7.2.dist-info/RECORD
